setuptools_ocrd/__init__.py
setuptools_ocrd/__main__.py
setuptools_ocrd/_get_version.py
setuptools_ocrd/_integration/__init__.py
setuptools_ocrd/_integration/setuptools.py
setuptools_ocrd/tests/__init__.py
setuptools_ocrd/tests/test_dummy.py
setuptools_ocrd-0.0.19.dist-info/LICENSE
setuptools_ocrd-0.0.19.dist-info/METADATA
setuptools_ocrd-0.0.19.dist-info/WHEEL
setuptools_ocrd-0.0.19.dist-info/entry_points.txt
setuptools_ocrd-0.0.19.dist-info/top_level.txt
setuptools_ocrd-0.0.19.dist-info/RECORD
