Metadata-Version: 2.1
Name: setuptools_ocrd
Version: 0.0.19
Summary: Manage your package version through ocrd-tool.json
Author-email: Mike Gerber <mike.gerber@sbb.spk-berlin.de>
Project-URL: Homepage, https://github.com/qurator-spk/setuptools_ocrd
Project-URL: Repository, https://github.com/qurator-spk/setuptools_ocrd.git
Keywords: ocr-d,setuptools
Classifier: Development Status :: 3 - Alpha
Classifier: Intended Audience :: Developers
Classifier: License :: OSI Approved :: Apache Software License
Classifier: Programming Language :: Python :: 3
Classifier: Programming Language :: Python :: 3 :: Only
Classifier: Topic :: Software Development :: Build Tools
Requires-Python: >=3.7
License-File: LICENSE
Provides-Extra: dev
Requires-Dist: pre-commit; extra == "dev"
Requires-Dist: pytest; extra == "dev"
